sabi.py
sabi-0.1.3.dist-info/LICENSE
sabi-0.1.3.dist-info/METADATA
sabi-0.1.3.dist-info/WHEEL
sabi-0.1.3.dist-info/entry_points.txt
sabi-0.1.3.dist-info/top_level.txt
sabi-0.1.3.dist-info/RECORD
