Metadata-Version: 2.1
Name: sabi
Version: 0.1.3
Summary: A simple module to translate plain English to Nigerian (Naija) pidgin English.
Home-page: https://github.com/techkaduna/sabi
Author: Kolawole Andrew
Author-email: andrewolakola@gmail.com
License: MIT
Classifier: Environment :: Console
Classifier: Intended Audience :: Education
Classifier: License :: OSI Approved :: MIT License
Classifier: Programming Language :: Python :: 3.6
Classifier: Topic :: Education
License-File: LICENSE
Requires-Dist: rich ==13.7.1
